{
  "current_phase": "models_complete",
  "last_deployment": null,
  "environments": {
    "development": "active",
    "staging": "not_deployed",
    "production": "not_deployed"
  },
  "pending_tasks": [
    {
      "id": "api_auth_system",
      "type": "feature",
      "priority": "high",
      "description": "Implement JWT authentication and user management endpoints",
      "assigned_skill": "full-stack-developer",
      "created": "2025-10-25T23:13:42.098340Z",
      "blocked_by": null
    },
    {
      "id": "api_event_management",
      "type": "feature",
      "priority": "high",
      "description": "Implement event CRUD endpoints with tier management",
      "assigned_skill": "full-stack-developer",
      "created": "2025-10-25T23:13:42.099904Z",
      "blocked_by": null
    },
    {
      "id": "api_ticket_purchase",
      "type": "feature",
      "priority": "high",
      "description": "Implement ticket purchase flow with inventory locking",
      "assigned_skill": "full-stack-developer",
      "created": "2025-10-25T23:13:42.101589Z",
      "blocked_by": null
    },
    {
      "id": "api_waitlist",
      "type": "feature",
      "priority": "medium",
      "description": "Implement waitlist management endpoints",
      "assigned_skill": "full-stack-developer",
      "created": "2025-10-25T23:13:42.103132Z",
      "blocked_by": null
    },
    {
      "id": "api_pydantic_schemas",
      "type": "feature",
      "priority": "high",
      "description": "Create all Pydantic schemas for API validation and serialization",
      "assigned_skill": "full-stack-developer",
      "created": "2025-10-26T11:20:44.529677Z",
      "blocked_by": null
    }
  ],
  "completed_tasks": [
    {
      "id": "api_core_setup",
      "type": "feature",
      "description": "Set up FastAPI project structure with SQLAlchemy models",
      "completed": "2025-10-25T23:16:23.190790Z",
      "skill": "full-stack-developer"
    }
  ],
  "blockers": [],
  "metrics": {
    "tests_passing": 0,
    "tests_failing": 0,
    "test_coverage": 0.0,
    "security_issues_open": 0,
    "security_issues_closed": 0,
    "deployment_frequency": "not_yet",
    "last_security_audit": null,
    "components_completed": 4,
    "components_remaining": 8,
    "estimated_completion": "55%",
    "models_completed": 11,
    "models_remaining": 0,
    "blockers_resolved": 1
  }
}